alphadoc/__init__.py
alphadoc/comment.py
alphadoc/docstring.py
alphadoc/init.py
alphadoc/main.py
alphadoc/style_fix.py
alphadoc/test_learn.py
alphadoc-1.0.3.dist-info/LICENSE
alphadoc-1.0.3.dist-info/METADATA
alphadoc-1.0.3.dist-info/WHEEL
alphadoc-1.0.3.dist-info/entry_points.txt
alphadoc-1.0.3.dist-info/top_level.txt
alphadoc-1.0.3.dist-info/RECORD
