Metadata-Version: 2.1
Name: alphadoc
Version: 1.0.3
Summary: Automatic style guide and docstrings generator for Python code
Home-page: https://github.com/MLH-Fellowship/alphadoc
License: MIT
Keywords: automation,docstring-generator,auto-docstrings,pep8
Platform: UNKNOWN
Classifier: Development Status :: 3 - Alpha
Classifier: Intended Audience :: Developers
Classifier: Programming Language :: Python :: 3
Classifier: License :: OSI Approved :: MIT License
Classifier: Operating System :: OS Independent
Classifier: Topic :: Software Development :: Libraries :: Python Modules
Classifier: Topic :: Software Development :: Documentation
Requires-Dist: click (==7.1.2)
Requires-Dist: setuptools (==50.3.2)
Requires-Dist: autopep8 (==1.5.4)
Requires-Dist: pathlib (==1.0.1)
